pylev.py
pylev-1.2.0.dist-info/DESCRIPTION.rst
pylev-1.2.0.dist-info/METADATA
pylev-1.2.0.dist-info/pydist.json
pylev-1.2.0.dist-info/RECORD
pylev-1.2.0.dist-info/top_level.txt
pylev-1.2.0.dist-info/WHEEL
