Metadata-Version: 2.0
Name: pylev
Version: 1.2.0
Summary: A pure Python Levenshtein implementation that's not freaking GPL'd.
Home-page: http://github.com/toastdriven/pylev
Author: Daniel Lindsley
Author-email: daniel@toastdriven.com
License: UNKNOWN
Platform: UNKNOWN
Classifier: Development Status :: 5 - Production/Stable
Classifier: Intended Audience :: Developers
Classifier: License :: OSI Approved :: BSD License
Classifier: Operating System :: OS Independent
Classifier: Programming Language :: Python
Classifier: Programming Language :: Python :: 3
